geocompy/__init__.py
geocompy/_version.py
geocompy/communication.py
geocompy/data.py
geocompy/py.typed
geocompy/geo/__init__.py
geocompy/geo/aus.py
geocompy/geo/aut.py
geocompy/geo/bap.py
geocompy/geo/bmm.py
geocompy/geo/cam.py
geocompy/geo/com.py
geocompy/geo/csv.py
geocompy/geo/ctl.py
geocompy/geo/dna.py
geocompy/geo/edm.py
geocompy/geo/ftr.py
geocompy/geo/gcdata.py
geocompy/geo/gctypes.py
geocompy/geo/img.py
geocompy/geo/kdm.py
geocompy/geo/mot.py
geocompy/geo/sup.py
geocompy/geo/tmc.py
geocompy/geo/wir.py
geocompy/gsi/__init__.py
geocompy/gsi/gsidata.py
geocompy/gsi/gsiformat.py
geocompy/gsi/gsitypes.py
geocompy/gsi/dna/__init__.py
geocompy/gsi/dna/measurements.py
geocompy/gsi/dna/settings.py
geocompy-1.0.0.dist-info/METADATA
geocompy-1.0.0.dist-info/WHEEL
geocompy-1.0.0.dist-info/licenses/LICENSE
geocompy-1.0.0.dist-info/RECORD
