Metadata-Version: 2.4
Name: geocompy
Version: 1.0.0
Summary: Surveying instrument automation through GeoCOM and other protocols.
Project-URL: Documentation, https://geocompy.readthedocs.io
Project-URL: Repository, https://github.com/MrClock8163/geocompy
Project-URL: Issues, https://github.com/MrClock8163/geocompy/issues
Project-URL: Changelog, https://geocompy.readthedocs.io/latest/changelog
Author-email: MrClock <mrclock8163@gmail.com>
License-Expression: MIT
License-File: LICENSE
Keywords: automation,geocom,gsi,leica,monitoring,surveying,totalstation
Classifier: Development Status :: 5 - Production/Stable
Classifier: Intended Audience :: Developers
Classifier: Intended Audience :: Science/Research
Classifier: License :: OSI Approved :: MIT License
Classifier: Operating System :: OS Independent
Classifier: Programming Language :: Python
Classifier: Programming Language :: Python :: 3
Classifier: Programming Language :: Python :: 3.11
Classifier: Programming Language :: Python :: 3.12
Classifier: Programming Language :: Python :: 3.13
Classifier: Programming Language :: Python :: 3.14
Classifier: Topic :: Education
Classifier: Topic :: Scientific/Engineering
Classifier: Topic :: Scientific/Engineering :: GIS
Classifier: Topic :: Software Development
Classifier: Topic :: Software Development :: Libraries
Classifier: Topic :: Software Development :: Libraries :: Python Modules
Classifier: Topic :: Terminals :: Serial
Classifier: Typing :: Typed
Requires-Python: >=3.11
Requires-Dist: pyserial~=3.5.0
